ImapLibrary2/__init__.py
ImapLibrary2/imap_proxy.py
ImapLibrary2/version.py
robotframework_imaplibrary2-0.4.11.dist-info/LICENSE
robotframework_imaplibrary2-0.4.11.dist-info/METADATA
robotframework_imaplibrary2-0.4.11.dist-info/WHEEL
robotframework_imaplibrary2-0.4.11.dist-info/top_level.txt
robotframework_imaplibrary2-0.4.11.dist-info/RECORD
