Metadata-Version: 2.1
Name: robotframework-imaplibrary2
Version: 0.4.11
Summary: A IMAP email testing library for Robot Framework
Home-page: https://github.com/lasselindqvist/robotframework-imaplibrary2
Author: Lasse Lindqvist
Author-email: lasselindqvist@users.noreply.github.com
License: Apache License, Version 2.0
Keywords: robot framework testing automation imap email mail softwaretesting
Platform: any
Classifier: Development Status :: 4 - Beta
Classifier: Framework :: Robot Framework
Classifier: Intended Audience :: Developers
Classifier: License :: OSI Approved :: Apache Software License
Classifier: Programming Language :: Python :: 2.7
Classifier: Programming Language :: Python :: 3.5
Classifier: Topic :: Software Development :: Testing
License-File: LICENSE
Requires-Dist: future
Requires-Dist: robotframework>=2.6.0
Requires-Dist: pysocks
